pythot
