Metadata-Version: 1.1
Name: Pythot
Version: 0.9.2.1
Summary: Software for learning first degree linear equation with visual solving.
Home-page: UNKNOWN
Author: Christophe Riolo
Author-email: riolo.christophe@gmail.com
License: GPLv3
Keywords: math mathematics education linear equation equations
Platform: UNKNOWN
Classifier: Development Status :: 3 - Alpha
Classifier: Environment :: X11 Applications :: Qt
Classifier: Intended Audience :: Education
Classifier: License :: OSI Approved :: GNU General Public License v3 (GPLv3)
Classifier: Natural Language :: French
Classifier: Operating System :: OS Independent
Classifier: Programming Language :: Python
Classifier: Programming Language :: Python :: 3
Classifier: Topic :: Education
Classifier: Topic :: Scientific/Engineering :: Mathematics
